MANIFEST.in
README.rst
setup.py
mqtttasky_groupme/__init__.py
mqtttasky_groupme/app.py
mqtttasky_groupme/bot_calls.py
mqtttasky_groupme/config_util.py
mqtttasky_groupme/gpio_status_light_util.py
mqtttasky_groupme/reconfig_util.py
mqtttasky_groupme/tasks.py
mqtttasky_groupme.egg-info/PKG-INFO
mqtttasky_groupme.egg-info/SOURCES.txt
mqtttasky_groupme.egg-info/dependency_links.txt
mqtttasky_groupme.egg-info/entry_points.txt
mqtttasky_groupme.egg-info/not-zip-safe
mqtttasky_groupme.egg-info/requires.txt
mqtttasky_groupme.egg-info/top_level.txt
mqtttasky_groupme/config/__init__.py
mqtttasky_groupme/config/groupme_bot_config.py
mqtttasky_groupme/config/mqtt_config.py
mqtttasky_groupme/images/clock-32x32.png