Metadata-Version: 2.1
Name: mqtttasky-groupme
Version: 0.1.4
Summary: GroupMe bot to schedule tasks, display and speak notifications, and publish them over MQTT.
Home-page: https://github.com/haasr/mqtttttttasky_groupme
Author: Ryan Haas
Author-email: haasrr@etsu.edu
License: MIT
Platform: UNKNOWN
Classifier: Intended Audience :: Other Audience
Classifier: License :: OSI Approved :: MIT License
Classifier: Programming Language :: Python :: 3 :: Only
Requires-Python: >=3.7
